{
    "player": {
        "name": "Ibrahim Adel",
        "firstName": "",
        "lastName": "",
        "slug": "ibrahim-adel",
        "shortName": "I. Adel",
        "position": "M",
        "jerseyNumber": "14",
        "height": 173,
        "userCount": 8441,
        "gender": "M",
        "id": 1008171,
        "marketValueCurrency": "EUR",
        "dateOfBirthTimestamp": 987984000,
        "proposedMarketValueRaw": {
            "value": 2600000,
            "currency": "EUR"
        },
        "fieldTranslations": {
            "nameTranslation": {
                "ar": "إبراهيم عادل",
                "bn": "ইব্রাহিম আদেল",
                "hi": "इब्राहीम अदेल"
            },
            "shortNameTranslation": {
                "ar": "إ. عادل",
                "bn": "আই. আদেল",
                "hi": "आई. अदेल"
            }
        }
    },
    "team": {
        "name": "Egypt",
        "slug": "egypt",
        "shortName": "Egypt",
        "gender": "M",
        "sport": {
            "name": "Football",
            "slug": "football",
            "id": 1
        },
        "userCount": 617607,
        "nameCode": "EGY",
        "ranking": 29,
        "disabled": false,
        "national": true,
        "type": 0,
        "id": 4758,
        "teamColors": {
            "primary": "#f00000",
            "secondary": "#ffffff",
            "text": "#ffffff"
        },
        "fieldTranslations": {
            "nameTranslation": {
                "ar": "مصر",
                "bn": "মিশর",
                "hi": "इजिप्ट",
                "ru": "Египет"
            },
            "shortNameTranslation": {}
        }
    },
    "statistics": {
        "totalPass": 9,
        "accuratePass": 7,
        "goalAssist": 0,
        "totalOwnHalfPasses": 1,
        "accurateOppositionHalfPasses": 7,
        "totalOppositionHalfPasses": 8,
        "duelLost": 4,
        "duelWon": 1,
        "challengeLost": 1,
        "dispossessed": 1,
        "totalContest": 3,
        "wonContest": 1,
        "unsuccessfulTouch": 1,
        "minutesPlayed": 14,
        "touches": 16,
        "rating": 6.4,
        "possessionLostCtrl": 6,
        "totalBallCarriesDistance": 84.473576148123,
        "ballCarriesCount": 7,
        "totalProgression": 62.248505854811,
        "bestBallCarryProgression": 26.963637018384,
        "totalProgressiveBallCarriesDistance": 30.355173677645,
        "progressiveBallCarriesCount": 1,
        "keyPass": 1,
        "ratingVersions": {
            "original": 6.4,
            "alternative": 6.5
        },
        "totalShots": 0,
        "passValueNormalized": -0.02,
        "dribbleValueNormalized": 0.18,
        "defensiveValueNormalized": -0.04,
        "statisticsType": {
            "sportSlug": "football",
            "statisticsType": "player"
        }
    },
    "position": "F",
    "extra": null
}