{"player":{"name":"Luiz Henrique","firstName":"Luiz Henrique","lastName":"","slug":"luiz-henrique","shortName":"L. Henrique","position":"M","jerseyNumber":"11","height":182,"userCount":25888,"gender":"M","sofascoreId":"luizhenrique_07","id":1035995,"marketValueCurrency":"EUR","dateOfBirthTimestamp":978393600,"proposedMarketValueRaw":{"value":25000000,"currency":"EUR"},"fieldTranslations":{"nameTranslation":{"ar":"\u0644\u0648\u064a\u0633 \u0647\u0646\u0631\u064a\u0643\u064a","bn":"\u09b2\u09c1\u0987\u099c \u09b9\u09c7\u09a8\u09b0\u09bf\u0995","hi":"\u0932\u0941\u0908\u091c\u093c \u0939\u0947\u0928\u0930\u093f\u0915","ru":"\u041b\u0443\u0438\u0441 \u042d\u043d\u0440\u0438\u043a\u0435"},"shortNameTranslation":{"ar":"\u0644. \u0647\u0646\u0631\u064a\u0643\u064a","bn":"\u098f\u09b2. \u09b9\u09c7\u09a8\u09b0\u09bf\u0995 \u09a8\u09c7\u099f\u09cb","hi":"\u090f\u0932. \u0939\u0947\u0928\u0930\u093f\u0915","ru":"\u041b. \u042d\u043d\u0440\u0438\u043a\u0435"}}},"team":{"name":"Brazil","slug":"brazil","shortName":"Brazil","gender":"M","sport":{"name":"Football","slug":"football","id":1},"userCount":2710522,"nameCode":"BRA","ranking":6,"disabled":false,"national":true,"type":0,"id":4748,"teamColors":{"primary":"#ffff00","secondary":"#009933","text":"#009933"},"fieldTranslations":{"nameTranslation":{"ar":"\u0627\u0644\u0628\u0631\u0627\u0632\u064a\u0644","bn":"\u09ac\u09cd\u09b0\u09be\u099c\u09bf\u09b2","hi":"\u092c\u094d\u0930\u093e\u091c\u0940\u0932","ru":"\u0411\u0440\u0430\u0437\u0438\u043b\u0438\u044f"},"shortNameTranslation":{}}},"statistics":{"totalPass":13,"accuratePass":12,"totalLongBalls":1,"accurateLongBalls":1,"goalAssist":0,"accurateOwnHalfPasses":6,"totalOwnHalfPasses":6,"accurateOppositionHalfPasses":6,"totalOppositionHalfPasses":7,"aerialWon":1,"duelLost":1,"duelWon":2,"challengeLost":1,"ballRecovery":2,"wasFouled":1,"minutesPlayed":28,"touches":14,"rating":7,"possessionLostCtrl":1,"expectedAssists":0.0417655,"topSpeed":28.42,"kilometersCovered":3.7,"numberOfSprints":5,"totalBallCarriesDistance":6.3935370492396,"ballCarriesCount":1,"totalProgression":4.9458139941462,"progressiveBallCarriesCount":0,"keyPass":1,"ratingVersions":{"original":7,"alternative":6.8},"totalShots":0,"passValueNormalized":0.33,"dribbleValueNormalized":0.01,"defensiveValueNormalized":-0.03,"metersCoveredRunningKm":0.58,"metersCoveredHighSpeedRunningKm":0.21,"metersCoveredSprintingKm":0.07,"statisticsType":{"sportSlug":"football","statisticsType":"player"}},"position":"F","extra":null}